mediqbox/loadpdf/__init__.py
mediqbox/loadpdf/doc.py
mediqbox/loadpdf/figure.py
mediqbox/loadpdf/helpers.py
mediqbox/loadpdf/rect.py
mediqbox/loadpdf/text.py
mediqbox_loadpdf-0.0.6.dist-info/METADATA
mediqbox_loadpdf-0.0.6.dist-info/WHEEL
mediqbox_loadpdf-0.0.6.dist-info/top_level.txt
mediqbox_loadpdf-0.0.6.dist-info/RECORD
