Metadata-Version: 2.1
Name: mediqbox-loadpdf
Version: 0.0.6
Summary: A mediqbox component for extracting figures and tables from PDF files
Requires-Dist: mediqbox-abc >=0.0.4
Requires-Dist: pymupdf
